p4print/__init__.py
p4print/setup.py
p4print-0.2.1.dist-info/METADATA
p4print-0.2.1.dist-info/WHEEL
p4print-0.2.1.dist-info/top_level.txt
p4print-0.2.1.dist-info/RECORD
