Metadata-Version: 2.2
Name: p4print
Version: 0.2.1
Summary: A lightweight package that lets you use p() instead of print().
Home-page: https://github.com/AshishKumarCS/p4print
Author: Ashish Kumar
Author-email: Ashish Kumar <ashish.jnu@outlook.com>
License: MIT
Classifier: Programming Language :: Python :: 3
Classifier: License :: OSI Approved :: MIT License
Classifier: Operating System :: OS Independent
Requires-Python: >=3.0
Dynamic: author
Dynamic: home-page
Dynamic: requires-python
